sphericart/jax/spherical_harmonics.py
sphericart/jax/dsph.py
sphericart/jax/ddsph.py
sphericart/jax/__init__.py
sphericart/jax/utils.py
sphericart/jax/sph.py
sphericart/jax/lib/sphericart_jax_cpu.cpython-312-darwin.so
sphericart_jax-1.0.5.dist-info/RECORD
sphericart_jax-1.0.5.dist-info/WHEEL
sphericart_jax-1.0.5.dist-info/top_level.txt
sphericart_jax-1.0.5.dist-info/METADATA
