Metadata-Version: 2.4
Name: sphericart-jax
Version: 1.0.5
Summary: JAX bindings to sphericart
Author: Filippo Bigi, Guillaume Fraux, Nicholas Browning, Michele Ceriotti, Felix Musil
License-Expression: Apache-2.0 OR MIT
Project-URL: homepage, https://github.com/lab-cosmo/sphericart
Project-URL: documentation, https://sphericart.readthedocs.io/en/latest/
Project-URL: repository, https://github.com/lab-cosmo/sphericart
Keywords: spherical harmonics,jax
Classifier: Development Status :: 4 - Beta
Classifier: Intended Audience :: Science/Research
Classifier: Operating System :: POSIX
Classifier: Operating System :: MacOS :: MacOS X
Classifier: Environment :: GPU :: NVIDIA CUDA
Classifier: Programming Language :: Python
Classifier: Programming Language :: Python :: 3
Classifier: Topic :: Scientific/Engineering
Classifier: Topic :: Scientific/Engineering :: Physics
Classifier: Topic :: Software Development :: Libraries
Classifier: Topic :: Software Development :: Libraries :: Python Modules
Requires-Python: >=3.9
Requires-Dist: jax<0.7.2,>=0.6.0
Requires-Dist: packaging
